emailtools/__init__.py
emailtools/emailtools.py
emailtools/providers.py
emailtools-0.0.5.dist-info/LICENSE
emailtools-0.0.5.dist-info/METADATA
emailtools-0.0.5.dist-info/WHEEL
emailtools-0.0.5.dist-info/top_level.txt
emailtools-0.0.5.dist-info/RECORD
