Metadata-Version: 2.1
Name: emailtools
Version: 0.0.5
Summary: A Python library for email suggestions and validations.
Home-page: https://github.com/armanyazdi/emailtools
Author: Arman Yazdi
License: MIT
Project-URL: Source, https://github.com/armanyazdi/emailtools
Project-URL: Documentation, https://pypi.org/project/emailtools
Keywords: email generator,email suggester,email validator,email
Classifier: License :: OSI Approved :: MIT License
Classifier: Natural Language :: Persian
Classifier: Natural Language :: English
Classifier: Programming Language :: Python
Classifier: Programming Language :: Python :: 3
Classifier: Programming Language :: Python :: 3.4
Classifier: Programming Language :: Python :: 3.5
Classifier: Programming Language :: Python :: 3.6
Classifier: Programming Language :: Python :: 3.7
Classifier: Programming Language :: Python :: 3.8
Classifier: Programming Language :: Python :: 3.9
Classifier: Programming Language :: Python :: 3.10
Classifier: Programming Language :: Python :: 3.11
Classifier: Topic :: Software Development :: Libraries
Classifier: Topic :: Software Development :: Libraries :: Python Modules
Classifier: Topic :: Software Development :: Localization
License-File: LICENSE
Requires-Dist: persian-names
